MANIFEST.in
README.rst
setup.py
bin/topser-pont
topser/__init__.py
topser/command_line.py
topser/pont.py
topser/test_command_line.py
topser.egg-info/PKG-INFO
topser.egg-info/SOURCES.txt
topser.egg-info/dependency_links.txt
topser.egg-info/not-zip-safe
topser.egg-info/requires.txt
topser.egg-info/top_level.txt