Metadata-Version: 1.1
Name: topser
Version: 0.2
Summary: The simple package
Home-page: http://github.com/vitakrya/topser
Author: Vita Kr
Author-email: vinder_2@mail.ru
License: MIT
Platform: UNKNOWN
Classifier: Development Status :: 3 - Alpha
Classifier: License :: OSI Approved :: MIT License
Classifier: Programming Language :: Python :: 3.4
Classifier: Topic :: Text Processing :: Linguistic
